phoenix_ai_audit_services/__init__.py
phoenix_ai_audit_services/api.py
phoenix_ai_audit_services/config.py
phoenix_ai_audit_services/crud.py
phoenix_ai_audit_services/main.py
phoenix_ai_audit_services/models.py
phoenix_ai_audit_services/storage/__init__.py
phoenix_ai_audit_services/storage/base.py
phoenix_ai_audit_services/storage/file.py
phoenix_ai_audit_services/storage/postgres.py
phoenix_ai_audit_services-0.6.6.dist-info/LICENSE
phoenix_ai_audit_services-0.6.6.dist-info/METADATA
phoenix_ai_audit_services-0.6.6.dist-info/WHEEL
phoenix_ai_audit_services-0.6.6.dist-info/entry_points.txt
phoenix_ai_audit_services-0.6.6.dist-info/RECORD
