Metadata-Version: 2.3
Name: phoenix-ai-audit-services
Version: 0.6.6
Summary: Audit, policy & governance service for Phoenix‑AI agents and tools
License: Apache-2.0
Author: Your Name
Author-email: you@example.com
Requires-Python: >=3.9,<3.14
Classifier: License :: OSI Approved :: Apache Software License
Classifier: Programming Language :: Python :: 3
Classifier: Programming Language :: Python :: 3.9
Classifier: Programming Language :: Python :: 3.10
Classifier: Programming Language :: Python :: 3.11
Classifier: Programming Language :: Python :: 3.12
Classifier: Programming Language :: Python :: 3.13
Requires-Dist: aiosqlite (>=0.20,<0.21)
Requires-Dist: asyncpg (>=0.29,<0.30)
Requires-Dist: fastapi (>=0.111.0,<0.112.0)
Requires-Dist: pydantic (>=2.7,<3.0)
Requires-Dist: pydantic-settings (>=2.2,<3.0)
Requires-Dist: python-dotenv (>=1.0,<2.0)
Requires-Dist: sqlalchemy[asyncio] (>=2.0,<3.0)
Requires-Dist: uvicorn[standard] (>=0.30.0,<0.31.0)
